phomber/__init__.py
phomber/phomber.py
phomber-3.1.1.dist-info/LICENSE
phomber-3.1.1.dist-info/METADATA
phomber-3.1.1.dist-info/WHEEL
phomber-3.1.1.dist-info/entry_points.txt
phomber-3.1.1.dist-info/top_level.txt
phomber-3.1.1.dist-info/RECORD
