Metadata-Version: 2.1
Name: phomber
Version: 3.1.1
Summary: `PH0MBER` a simple yet powerful osint framework for reconnaissance and information gathering
Author: s41r4j
Maintainer: s41r4j
License: GNU GENERAL PUBLIC LICENSE
Project-URL: Homepage, https://github.com/s41r4j/phomber
Project-URL: Bug Tracker, https://github.com/s41r4j/phomber/issues
Keywords: python,hacking,pentesting,phomber,reverse,lookup,osint,framework,tool,s41r4j
Classifier: Programming Language :: Python :: 3
Classifier: License :: OSI Approved :: GNU General Public License v3 (GPLv3)
Classifier: Operating System :: OS Independent
Classifier: Environment :: Console
Classifier: Development Status :: 5 - Production/Stable
Requires-Python: >=3.7
License-File: LICENSE
Requires-Dist: requests
Requires-Dist: prompt-toolkit
Requires-Dist: uuid
Requires-Dist: psutil
Requires-Dist: beautifulsoup4
Requires-Dist: phonenumbers
Requires-Dist: mac-vendor-lookup
Requires-Dist: python-whois
Requires-Dist: dnspython
